{
	"source": "https://id.wikipedia.org/wiki/Kategori:Kecamatan_di_Kota_Balikpapan",
	"scraped_at": "2023-01-25T10:10:57.912Z",
	"kabupaten": {
		"id": 8,
		"name": "Kota Balikpapan",
		"emblem": "https://upload.wikimedia.org/wikipedia/commons/4/4e/Coat_of_arms_of_Balikpapan.svg"
	},
	"data": [
		{
			"id": 1,
			"name": "Balikpapan Barat"
		},
		{
			"id": 2,
			"name": "Balikpapan Kota"
		},
		{
			"id": 3,
			"name": "Balikpapan Selatan"
		},
		{
			"id": 4,
			"name": "Balikpapan Tengah"
		},
		{
			"id": 5,
			"name": "Balikpapan Timur"
		},
		{
			"id": 6,
			"name": "Balikpapan Utara"
		}
	]
}