{
	"source": "https://id.wikipedia.org/wiki/Daftar_kabupaten_dan_kota_di_Aceh",
	"scraped_at": "2023-01-23T04:18:50.851Z",
	"provinsi": {
		"id": 1,
		"code": "11",
		"name": "Aceh",
		"image_url": "https://upload.wikimedia.org/wikipedia/commons/4/41/Coat_of_arms_of_Aceh.svg"
	},
	"data": {
		"kabupaten": [
			{
				"id": 1,
				"name": "Kabupaten Aceh Barat",
				"image_url": "https://upload.wikimedia.org/wikipedia/commons/0/0c/Seal_of_Aceh_Barat_Regency.svg",
				"capital": "Meulaboh"
			},
			{
				"id": 2,
				"name": "Kabupaten Aceh Barat Daya",
				"image_url": "https://upload.wikimedia.org/wikipedia/commons/e/ea/Lambang_Kabupaten_Aceh_Barat_Daya.png",
				"capital": "Blangpidie"
			},
			{
				"id": 3,
				"name": "Kabupaten Aceh Besar",
				"image_url": "https://upload.wikimedia.org/wikipedia/commons/c/c8/Lambang_Kabupaten_Aceh_Besar.png",
				"capital": "Kota Jantho"
			},
			{
				"id": 4,
				"name": "Kabupaten Aceh Jaya",
				"image_url": "https://upload.wikimedia.org/wikipedia/commons/a/ac/Coat_of_arms_of_Aceh_Jaya.jpg",
				"capital": "Calang"
			},
			{
				"id": 5,
				"name": "Kabupaten Aceh Selatan",
				"image_url": "https://upload.wikimedia.org/wikipedia/commons/0/01/Lambang_Kabupaten_Aceh_Selatan.png",
				"capital": "Tapak Tuan"
			},
			{
				"id": 6,
				"name": "Kabupaten Aceh Singkil",
				"image_url": "https://upload.wikimedia.org/wikipedia/commons/7/75/Lambang_Kabupaten_Aceh_Singkil.png",
				"capital": "Singkil"
			},
			{
				"id": 7,
				"name": "Kabupaten Aceh Tamiang",
				"image_url": "https://upload.wikimedia.org/wikipedia/commons/3/35/Lambang_Kabupaten_Aceh_Tamiang.png",
				"capital": "Karang Baru"
			},
			{
				"id": 8,
				"name": "Kabupaten Aceh Tengah",
				"image_url": "https://upload.wikimedia.org/wikipedia/commons/d/d1/Lambang_Kabupaten_Aceh_Tengah.png",
				"capital": "Takengon"
			},
			{
				"id": 9,
				"name": "Kabupaten Aceh Tenggara",
				"image_url": "https://upload.wikimedia.org/wikipedia/commons/e/e6/Lambang_Kabupaten_Aceh_Tenggara.png",
				"capital": "Kutacane"
			},
			{
				"id": 10,
				"name": "Kabupaten Aceh Timur",
				"image_url": "https://upload.wikimedia.org/wikipedia/commons/a/a0/Lambang_Kabupaten_Aceh_Timur.png",
				"capital": "Idi Rayeuk"
			},
			{
				"id": 11,
				"name": "Kabupaten Aceh Utara",
				"image_url": "https://upload.wikimedia.org/wikipedia/commons/f/fe/Lambang_kab_acehutara.png",
				"capital": "Lhoksukon"
			},
			{
				"id": 12,
				"name": "Kabupaten Bener Meriah",
				"image_url": "https://upload.wikimedia.org/wikipedia/commons/a/a0/Lambang_Kabupaten_Bener_Meriah.png",
				"capital": "Simpang Tiga Redelong"
			},
			{
				"id": 13,
				"name": "Kabupaten Bireuen",
				"image_url": "https://upload.wikimedia.org/wikipedia/commons/0/0a/Logo_Bireuen.jpg",
				"capital": "Bireuen"
			},
			{
				"id": 14,
				"name": "Kabupaten Gayo Lues",
				"image_url": "https://upload.wikimedia.org/wikipedia/commons/7/7b/Lambang_Gayo_Lues.png",
				"capital": "Blang Kejeren"
			},
			{
				"id": 15,
				"name": "Kabupaten Nagan Raya",
				"image_url": "https://upload.wikimedia.org/wikipedia/commons/e/eb/Lambang_Kabupaten_Nagan_Raya.png",
				"capital": "Suka Makmue"
			},
			{
				"id": 16,
				"name": "Kabupaten Pidie",
				"image_url": "https://upload.wikimedia.org/wikipedia/commons/d/dc/Logo_Kabupaten_Pidie.jpg",
				"capital": "Sigli"
			},
			{
				"id": 17,
				"name": "Kabupaten Pidie Jaya",
				"image_url": "https://upload.wikimedia.org/wikipedia/commons/4/42/Lambang_Kabupaten_Pidie_Jaya.png",
				"capital": "Meureudu"
			},
			{
				"id": 18,
				"name": "Kabupaten Simeulue",
				"image_url": "https://upload.wikimedia.org/wikipedia/commons/2/29/LOGO_KABUPATEN_SIMEULUE.png",
				"capital": "Sinabang"
			},
			{
				"id": 19,
				"name": "Kota Banda Aceh",
				"image_url": "https://upload.wikimedia.org/wikipedia/commons/7/7e/Lambang_Kota_Banda_Aceh.png",
				"capital": "-"
			},
			{
				"id": 20,
				"name": "Kota Langsa",
				"image_url": "https://upload.wikimedia.org/wikipedia/commons/4/4a/Pemko_langsa.jpg",
				"capital": "-"
			},
			{
				"id": 21,
				"name": "Kota Lhokseumawe",
				"image_url": "https://upload.wikimedia.org/wikipedia/commons/6/6a/Lambang_Kota_Lhokseumawe.gif",
				"capital": "-"
			},
			{
				"id": 22,
				"name": "Kota Sabang",
				"image_url": "https://upload.wikimedia.org/wikipedia/commons/7/79/Lambang_Kota_Sabang.png",
				"capital": "-"
			},
			{
				"id": 23,
				"name": "Kota Subulussalam",
				"image_url": "https://upload.wikimedia.org/wikipedia/commons/2/27/Lambang_Kota_Subulussalam.png",
				"capital": "-"
			}
		]
	}
}